<annotation>
	<folder>image</folder>
	<filename>lime_034.jpg</filename>
	<path>/Users/krxw/Me/TGR15/im/image/lime_034.jpg</path>
	<source>
		<database>Unknown</database>
	</source>
	<size>
		<width>800</width>
		<height>800</height>
		<depth>3</depth>
	</size>
	<segmented>0</segmented>
	<object>
		<name>lime</name>
		<pose>Unspecified</pose>
		<truncated>0</truncated>
		<difficult>0</difficult>
		<bndbox>
			<xmin>407</xmin>
			<ymin>354</ymin>
			<xmax>556</xmax>
			<ymax>505</ymax>
		</bndbox>
	</object>
</annotation>
